{
  "Rows": {
    "RowColumnAttachedInfos": {
      "7": {
        "GridRowColumnDefinition": {
          "DesignLengthInPixel": 28.0
        }
      },
      "8": {
        "GridRowColumnDefinition": {
          "DesignLengthInPixel": 28.0
        }
      }
    },
    "Count": 23
  },
  "Cols": {
    "RowColumnAttachedInfos": {
      "0": {
        "GridRowColumnDefinition": {
          "DesignLengthInPixel": 20.0
        }
      },
      "1": {
        "GridRowColumnDefinition": {
          "DesignLengthInPixel": 30.0
        }
      },
      "2": {
        "GridRowColumnDefinition": {
          "DesignLengthInPixel": 30.0
        }
      },
      "3": {
        "GridRowColumnDefinition": {
          "DesignLengthInPixel": 50.0,
          "IsHidden": true
        }
      },
      "4": {
        "GridRowColumnDefinition": {
          "DesignLengthInPixel": 50.0,
          "IsHidden": true
        }
      },
      "5": {
        "GridRowColumnDefinition": {
          "DesignLengthInPixel": 50.0,
          "IsHidden": true
        }
      },
      "6": {
        "GridRowColumnDefinition": {
          "DesignLengthInPixel": 30.0
        }
      },
      "7": {
        "GridRowColumnDefinition": {
          "DesignLengthInPixel": 30.0
        }
      },
      "8": {
        "GridRowColumnDefinition": {
          "DesignLengthInPixel": 30.0
        }
      },
      "9": {
        "GridRowColumnDefinition": {
          "DesignLengthInPixel": 30.0
        }
      },
      "10": {
        "GridRowColumnDefinition": {
          "DesignLengthInPixel": 30.0
        }
      },
      "11": {
        "GridRowColumnDefinition": {
          "DesignLengthInPixel": 30.0
        }
      },
      "12": {
        "GridRowColumnDefinition": {
          "DesignLengthInPixel": 30.0
        }
      },
      "13": {
        "GridRowColumnDefinition": {
          "DesignLengthInPixel": 30.0
        }
      },
      "14": {
        "GridRowColumnDefinition": {
          "DesignLengthInPixel": 30.0
        }
      },
      "15": {
        "GridRowColumnDefinition": {
          "DesignLengthInPixel": 30.0
        }
      },
      "16": {
        "GridRowColumnDefinition": {
          "DesignLengthInPixel": 30.0
        }
      },
      "17": {
        "GridRowColumnDefinition": {
          "DesignLengthInPixel": 30.0
        }
      },
      "18": {
        "GridRowColumnDefinition": {
          "DesignLengthInPixel": 30.0
        }
      },
      "19": {
        "GridRowColumnDefinition": {
          "DesignLengthInPixel": 30.0
        }
      },
      "20": {
        "GridRowColumnDefinition": {
          "DesignLengthInPixel": 30.0
        }
      },
      "21": {
        "GridRowColumnDefinition": {
          "DesignLengthInPixel": 30.0
        }
      },
      "22": {
        "GridRowColumnDefinition": {
          "DesignLengthInPixel": 30.0
        }
      },
      "23": {
        "GridRowColumnDefinition": {
          "DesignLengthInPixel": 30.0
        }
      },
      "24": {
        "GridRowColumnDefinition": {
          "DesignLengthInPixel": 30.0
        }
      },
      "25": {
        "GridRowColumnDefinition": {
          "DesignLengthInPixel": 30.0
        }
      },
      "26": {
        "GridRowColumnDefinition": {
          "DesignLengthInPixel": 30.0
        }
      },
      "27": {
        "GridRowColumnDefinition": {
          "DesignLengthInPixel": 30.0
        }
      },
      "28": {
        "GridRowColumnDefinition": {
          "DesignLengthInPixel": 30.0
        }
      },
      "29": {
        "GridRowColumnDefinition": {
          "DesignLengthInPixel": 30.0
        }
      },
      "30": {
        "GridRowColumnDefinition": {
          "DesignLengthInPixel": 30.0
        }
      },
      "31": {
        "GridRowColumnDefinition": {
          "DesignLengthInPixel": 30.0
        }
      },
      "32": {
        "GridRowColumnDefinition": {
          "DesignLengthInPixel": 30.0
        }
      },
      "33": {
        "GridRowColumnDefinition": {
          "DesignLengthInPixel": 30.0
        }
      },
      "34": {
        "GridRowColumnDefinition": {
          "DesignLengthInPixel": 30.0
        }
      },
      "35": {
        "GridRowColumnDefinition": {
          "DesignLengthInPixel": 30.0
        }
      },
      "36": {
        "GridRowColumnDefinition": {
          "DesignLengthInPixel": 30.0
        }
      },
      "37": {
        "GridRowColumnDefinition": {
          "DesignLengthInPixel": 30.0
        }
      },
      "38": {
        "GridRowColumnDefinition": {
          "DesignLengthInPixel": 30.0
        }
      },
      "39": {
        "GridRowColumnDefinition": {
          "DesignLengthInPixel": 30.0
        }
      },
      "40": {
        "GridRowColumnDefinition": {
          "DesignLengthInPixel": 30.0
        }
      },
      "41": {
        "GridRowColumnDefinition": {
          "DesignLengthInPixel": 20.0
        }
      },
      "42": {
        "GridRowColumnDefinition": {
          "DesignLengthInPixel": 20.0
        }
      }
    },
    "InLogicalVisibleIndexes": [
      3,
      4,
      5
    ],
    "Count": 43,
    "DefaultSize": 30.0
  },
  "Values": {
    "1,1": "编码",
    "1,17": "名称",
    "1,30": "规格",
    "4,1": "总需求",
    "4,17": "已配料",
    "4,30": "还需",
    "7,6": "批次",
    "7,27": "净有效数量",
    "7,32": "净实物",
    "7,37": "本次使用",
    "8,37": 0,
    "20,1": "合计选择",
    "20,21": "选择余额",
    "20,34": "确认"
  },
  "Formulas": {
    "4,34": "I5-V5",
    "20,25": "AI5-L21",
    "20,11": "SUM(AL9)"
  },
  "AttachInfos": {
    "1,8": {
      "CellType": {
        "$type": "Forguncy.TextCellType, ServerDesignerCommon",
        "SavedValidators": [
          {
            "$type": "Forguncy.CellTypes.Models.UniqueValidadator, ServerDesignerCommon"
          }
        ],
        "TemplateKey": "样式2"
      }
    },
    "1,21": {
      "CellType": {
        "$type": "Forguncy.TextCellType, ServerDesignerCommon",
        "SavedValidators": [
          {
            "$type": "Forguncy.CellTypes.Models.UniqueValidadator, ServerDesignerCommon"
          }
        ],
        "TemplateKey": "样式2"
      }
    },
    "1,34": {
      "CellType": {
        "$type": "Forguncy.TextCellType, ServerDesignerCommon",
        "SavedValidators": [
          {
            "$type": "Forguncy.CellTypes.Models.UniqueValidadator, ServerDesignerCommon"
          }
        ],
        "TemplateKey": "样式2"
      }
    },
    "4,8": {
      "CellType": {
        "$type": "Forguncy.NumberCellType, ServerDesignerCommon",
        "DecimalPlacesNumber": 4,
        "TemplateKey": "样式2"
      }
    },
    "4,21": {
      "CellType": {
        "$type": "Forguncy.NumberCellType, ServerDesignerCommon",
        "DecimalPlacesNumber": 4,
        "TemplateKey": "样式2"
      }
    },
    "4,34": {
      "CellType": {
        "$type": "Forguncy.NumberCellType, ServerDesignerCommon",
        "DecimalPlacesNumber": 4,
        "TemplateKey": "样式2"
      }
    },
    "7,1": {
      "ListViewInfo": {
        "Name": "表格1",
        "TableName": "净可用库存",
        "RowIndex": 7,
        "ColumnIndex": 1,
        "RowCount": 12,
        "ColumnCount": 40,
        "SqlCondition": {
          "$type": "ForguncyDataAccess.RelationSqlCondition, ForguncyDataAccess",
          "SubConditions": [
            {
              "$type": "ForguncyDataAccess.GeneralCESqlCondition, ForguncyDataAccess",
              "ColumnBindingInfo": {
                "TableName": "净可用库存",
                "ColumnName": "cInvCode",
                "GUID": "43125d82-8d4b-43be-8f9c-a41a16eba658"
              },
              "Value": {
                "$type": "Forguncy.Model.FormulaReferObject, ServerDesignerCommon",
                "SerializeProperty": "=库存参照!$I$2"
              }
            },
            {
              "$type": "ForguncyDataAccess.GeneralCESqlCondition, ForguncyDataAccess",
              "CompareType": 2,
              "ColumnBindingInfo": {
                "TableName": "净可用库存",
                "ColumnName": "实际库存",
                "GUID": "3c933ca5-5ed1-447e-8c8d-464bcfc5e40b"
              },
              "Value": "0"
            }
          ]
        },
        "TopCondition": null,
        "ListViewStyleName": "样式1",
        "ShowColumnHeaderInDesigner": true,
        "IsRowHeaderVisible": true,
        "IsRowHeaderCheckBoxVisible": true,
        "ShowEditStatusIcon": true,
        "UseSimpleBar": true,
        "AllowEditInListview": true,
        "AlwaysReservedSelections": true,
        "IsSingleSelection": true,
        "ColumnOperation": 2,
        "CommitType": 1,
        "DoNotLoadDataWhenLoadPage": true
      }
    },
    "8,3": {
      "BindingInfo": {
        "TableName": "净可用库存",
        "ColumnName": "cInvCode",
        "GUID": "f8113987-ab59-48cd-83a9-fd56c3c29712"
      }
    },
    "8,4": {
      "BindingInfo": {
        "TableName": "净可用库存",
        "ColumnName": "cInvCode",
        "GUID": "6ce578db-e210-46f4-b5da-77a84ab18059",
        "RelationBinding": {
          "RelatedTable": "inventory",
          "RelatedColumn": "cInvCode",
          "DisplayColumn": "cInvName"
        }
      }
    },
    "8,5": {
      "BindingInfo": {
        "TableName": "净可用库存",
        "ColumnName": "cInvCode",
        "GUID": "720ae3be-e94a-49bc-9151-5850ef767d31",
        "RelationBinding": {
          "RelatedTable": "inventory",
          "RelatedColumn": "cInvCode",
          "DisplayColumn": "cInvStd"
        }
      }
    },
    "8,6": {
      "BindingInfo": {
        "TableName": "净可用库存",
        "ColumnName": "cBatch",
        "GUID": "eba45272-e4c4-4a9d-9967-2b6d54a25d3f"
      }
    },
    "8,12": {
      "BindingInfo": {
        "TableName": "净可用库存",
        "ColumnName": "实际含量",
        "GUID": "ca9a7d40-4a05-4d62-8a2b-853f22a24116"
      }
    },
    "8,14": {
      "BindingInfo": {
        "TableName": "净可用库存",
        "ColumnName": "实际库存",
        "GUID": "a3f8be3f-ad5f-4049-9953-1110ce8ce074"
      }
    },
    "8,18": {
      "BindingInfo": {
        "TableName": "净可用库存",
        "ColumnName": "实际件数",
        "GUID": "e91615cb-606b-40ec-ac4d-a1f636e9b354"
      }
    },
    "8,23": {
      "BindingInfo": {
        "TableName": "净可用库存",
        "ColumnName": "合计占用",
        "GUID": "93df67a8-985c-4443-ac22-92b161923d4f"
      }
    },
    "8,27": {
      "BindingInfo": {
        "TableName": "净可用库存",
        "ColumnName": "iquantity",
        "GUID": "3d2f1cbb-fc83-49b2-a586-8fa36a8c2118"
      },
      "CellType": {
        "$type": "Forguncy.NumberCellType, ServerDesignerCommon",
        "DecimalPlacesNumber": 4
      },
      "DataValidationInfo": {
        "NumberType": 2,
        "FirstParamValue": "0",
        "SecondParamValue": {
          "$type": "Forguncy.Model.FormulaReferObject, ServerDesignerCommon",
          "SerializeProperty": "=库存参照!AB9"
        }
      }
    },
    "8,32": {
      "BindingInfo": {
        "TableName": "净可用库存",
        "ColumnName": "inum",
        "GUID": "d016320f-d2ad-4512-9e20-646c6eb6f2d6"
      },
      "CellType": {
        "$type": "Forguncy.NumberCellType, ServerDesignerCommon",
        "DecimalPlacesNumber": 4
      }
    },
    "8,37": {
      "BindingInfo": {
        "TableName": "净可用库存",
        "ColumnName": "本次使用",
        "GUID": "65fcb9c7-aa49-47d6-9de5-36bf06d10321"
      },
      "CellType": {
        "$type": "Forguncy.NumberCellType, ServerDesignerCommon",
        "DecimalPlacesNumber": 4,
        "CellDefaultValue": 0.0
      },
      "DataValidationInfo": {
        "IgnoreBlank": false
      }
    },
    "20,11": {
      "CellType": {
        "$type": "Forguncy.NumberCellType, ServerDesignerCommon",
        "DecimalPlacesNumber": 4,
        "TemplateKey": "样式2"
      }
    },
    "20,21": {
      "CellType": {
        "$type": "Forguncy.HyperlinkCellType, ServerDesignerCommon",
        "CommandList": [
          {
            "$type": "Forguncy.Model.UpdateListviewCommand, ServerDesignerCommon",
            "ListviewName": "表格1",
            "UpdateValues": [
              {
                "Column": {
                  "$type": "Forguncy.Model.FormulaReferObject, ServerDesignerCommon",
                  "SerializeProperty": "=库存参照!AL9"
                },
                "Value": {
                  "$type": "Forguncy.Model.FormulaReferObject, ServerDesignerCommon",
                  "SerializeProperty": "=库存参照!Z21"
                }
              }
            ]
          }
        ],
        "Text": "选择余额",
        "ClickMode": 1
      }
    },
    "20,25": {
      "CellType": {
        "$type": "Forguncy.NumberCellType, ServerDesignerCommon",
        "DecimalPlacesNumber": 4,
        "TemplateKey": "样式2"
      }
    },
    "20,34": {
      "CellType": {
        "$type": "Forguncy.ButtonCellType, ServerDesignerCommon",
        "CommandList": [
          {
            "$type": "Forguncy.Model.ConditionCommand, ServerDesignerCommon",
            "ConditionAndCommandPairList": [
              {
                "Condition": {
                  "$type": "Forguncy.Model.IfCondition, ServerDesignerCommon",
                  "param": {
                    "$type": "Forguncy.Model.IfConditionPageElementParam, ServerDesignerCommon",
                    "cellLocations": [
                      {
                        "SerializeProperty": "=库存参照!L21"
                      }
                    ]
                  },
                  "value": {
                    "$type": "Forguncy.Model.FormulaReferObject, ServerDesignerCommon",
                    "SerializeProperty": "=库存参照!AI5"
                  }
                },
                "CommandList": [
                  {
                    "$type": "PassListviewDataCommand.PassListviewDataCommand, PassListviewDataCommand",
                    "PassRowMode": 2,
                    "PassValueItems": [
                      {
                        "SourceCell": {
                          "$type": "Forguncy.Model.FormulaReferObject, ServerDesignerCommon",
                          "SerializeProperty": "=库存参照!G9"
                        },
                        "TargetCell": {
                          "$type": "Forguncy.Model.FormulaReferObject, ServerDesignerCommon",
                          "SerializeProperty": "=配料后更改!R11"
                        }
                      },
                      {
                        "SourceCell": {
                          "$type": "Forguncy.Model.FormulaReferObject, ServerDesignerCommon",
                          "SerializeProperty": "=库存参照!AL9"
                        },
                        "TargetCell": {
                          "$type": "Forguncy.Model.FormulaReferObject, ServerDesignerCommon",
                          "SerializeProperty": "=配料后更改!AF11"
                        }
                      },
                      {
                        "SourceCell": {
                          "$type": "Forguncy.Model.FormulaReferObject, ServerDesignerCommon",
                          "SerializeProperty": "=库存参照!D9"
                        },
                        "TargetCell": {
                          "$type": "Forguncy.Model.FormulaReferObject, ServerDesignerCommon",
                          "SerializeProperty": "=配料后更改!D11"
                        }
                      },
                      {
                        "SourceCell": {
                          "$type": "Forguncy.Model.FormulaReferObject, ServerDesignerCommon",
                          "SerializeProperty": "=库存参照!E9"
                        },
                        "TargetCell": {
                          "$type": "Forguncy.Model.FormulaReferObject, ServerDesignerCommon",
                          "SerializeProperty": "=配料后更改!H11"
                        }
                      },
                      {
                        "SourceCell": {
                          "$type": "Forguncy.Model.FormulaReferObject, ServerDesignerCommon",
                          "SerializeProperty": "=库存参照!F9"
                        },
                        "TargetCell": {
                          "$type": "Forguncy.Model.FormulaReferObject, ServerDesignerCommon",
                          "SerializeProperty": "=配料后更改!N11"
                        }
                      },
                      {
                        "SourceCell": {
                          "$type": "Forguncy.Model.FormulaReferObject, ServerDesignerCommon",
                          "SerializeProperty": "=库存参照!M9"
                        },
                        "TargetCell": {
                          "$type": "Forguncy.Model.FormulaReferObject, ServerDesignerCommon",
                          "SerializeProperty": "=配料后更改!AD11"
                        }
                      }
                    ],
                    "Source": {
                      "$type": "Forguncy.Model.FormulaReferObject, ServerDesignerCommon",
                      "SerializeProperty": "=库存参照!G9"
                    },
                    "Target": {
                      "$type": "Forguncy.Model.FormulaReferObject, ServerDesignerCommon",
                      "SerializeProperty": "=配料后更改!R11"
                    }
                  },
                  {
                    "$type": "Forguncy.Model.ClosePopupCommand, ServerDesignerCommon"
                  }
                ],
                "ID": "fd4bac27-9afc-43ec-8758-c088598b2765"
              },
              {
                "Condition": {
                  "$type": "Forguncy.Model.IfCondition, ServerDesignerCommon",
                  "param": {
                    "$type": "Forguncy.Model.IfConditionPageElementParam, ServerDesignerCommon",
                    "cellLocations": [
                      {
                        "SerializeProperty": "=库存参照!AI5"
                      }
                    ]
                  },
                  "value": {
                    "$type": "Forguncy.Model.FormulaReferObject, ServerDesignerCommon",
                    "SerializeProperty": "=库存参照!L21"
                  },
                  "compareType": 1
                },
                "CommandList": [
                  {
                    "$type": "Forguncy.Model.ShowMessageCommand, ServerDesignerCommon",
                    "MessageFormula": "配料数不正确"
                  }
                ],
                "ID": "3adbf539-5b76-40da-b1c5-fed7c1bb69bf"
              }
            ]
          }
        ],
        "Text": "确认",
        "TemplateKey": "样式5"
      }
    }
  },
  "StyleDatas": {
    "Styles": [
      {
        "HorizontalAlignment": 0
      },
      {
        "Formatter": 1,
        "HorizontalAlignment": 0
      },
      {
        "FontFamily": 2,
        "Formatter": 3,
        "HorizontalAlignment": 0
      },
      {
        "FontFamily": 2
      },
      {
        "FontFamily": 2,
        "Formatter": 1,
        "HorizontalAlignment": 0
      },
      {
        "FontFamily": 2,
        "HorizontalAlignment": 0
      },
      {
        "FontFamily": 2,
        "Formatter": 4,
        "HorizontalAlignment": 0
      },
      {
        "Formatter": 4,
        "HorizontalAlignment": 0
      },
      {
        "FontWeight": 5,
        "Foreground": 6,
        "HorizontalAlignment": 0,
        "Underline": true
      },
      {
        "FontWeight": 5,
        "HorizontalAlignment": 0
      },
      {
        "FontSize": 18.666666666666664,
        "FontWeight": 5
      }
    ],
    "Types": {
      "Strs": [
        "Center",
        "@",
        "Body",
        "[AUTO]General",
        "#,##0.0000",
        "Bold",
        "Blue"
      ]
    },
    "CellStyles": {
      "1,1": 0,
      "1,8": 1,
      "1,15": 0,
      "1,16": 0,
      "1,17": 2,
      "1,18": 3,
      "1,19": 3,
      "1,20": 3,
      "1,21": 4,
      "1,28": 5,
      "1,29": 5,
      "1,30": 2,
      "1,31": 3,
      "1,32": 3,
      "1,33": 3,
      "1,34": 4,
      "2,15": 0,
      "2,16": 0,
      "2,17": 3,
      "2,18": 3,
      "2,19": 3,
      "2,20": 3,
      "2,28": 5,
      "2,29": 5,
      "2,30": 3,
      "2,31": 3,
      "2,32": 3,
      "2,33": 3,
      "3,1": 0,
      "3,2": 0,
      "3,3": 0,
      "3,4": 0,
      "3,5": 0,
      "3,6": 0,
      "3,7": 0,
      "3,8": 0,
      "3,9": 0,
      "3,10": 0,
      "3,11": 0,
      "3,12": 0,
      "3,13": 0,
      "3,14": 0,
      "3,15": 0,
      "3,16": 0,
      "3,17": 5,
      "3,18": 5,
      "3,19": 5,
      "3,20": 5,
      "3,21": 5,
      "3,22": 5,
      "3,23": 5,
      "3,24": 5,
      "3,25": 5,
      "3,26": 5,
      "3,27": 5,
      "3,28": 0,
      "3,29": 0,
      "3,30": 5,
      "3,31": 5,
      "3,32": 5,
      "3,33": 5,
      "3,34": 5,
      "3,35": 5,
      "3,36": 5,
      "3,37": 5,
      "3,38": 5,
      "3,39": 5,
      "3,40": 5,
      "4,1": 5,
      "4,2": 3,
      "4,6": 3,
      "4,7": 3,
      "4,8": 6,
      "4,9": 3,
      "4,10": 3,
      "4,11": 3,
      "4,12": 3,
      "4,13": 3,
      "4,14": 3,
      "4,15": 5,
      "4,16": 5,
      "4,17": 2,
      "4,18": 3,
      "4,19": 3,
      "4,20": 3,
      "4,21": 6,
      "4,22": 3,
      "4,23": 3,
      "4,24": 3,
      "4,25": 3,
      "4,26": 3,
      "4,27": 3,
      "4,28": 5,
      "4,29": 5,
      "4,30": 2,
      "4,34": 6,
      "4,35": 3,
      "4,36": 3,
      "4,37": 3,
      "4,38": 3,
      "4,39": 3,
      "4,40": 3,
      "5,1": 3,
      "5,2": 3,
      "5,6": 3,
      "5,7": 3,
      "5,8": 3,
      "5,9": 3,
      "5,10": 3,
      "5,11": 3,
      "5,12": 3,
      "5,13": 3,
      "5,14": 3,
      "5,15": 5,
      "5,16": 5,
      "5,17": 3,
      "5,18": 3,
      "5,19": 3,
      "5,20": 3,
      "5,21": 3,
      "5,22": 3,
      "5,23": 3,
      "5,24": 3,
      "5,25": 3,
      "5,26": 3,
      "5,27": 3,
      "5,28": 5,
      "5,29": 5,
      "5,34": 3,
      "5,35": 3,
      "5,36": 3,
      "5,37": 3,
      "5,38": 3,
      "5,39": 3,
      "5,40": 3,
      "7,1": 0,
      "7,2": 0,
      "7,3": 0,
      "7,4": 0,
      "7,5": 0,
      "7,6": 0,
      "7,12": 0,
      "7,14": 0,
      "7,18": 0,
      "7,22": 0,
      "7,23": 0,
      "7,27": 2,
      "7,32": 2,
      "7,37": 0,
      "8,1": 0,
      "8,2": 0,
      "8,3": 0,
      "8,4": 0,
      "8,5": 0,
      "8,6": 0,
      "8,12": 0,
      "8,14": 5,
      "8,18": 5,
      "8,19": 3,
      "8,20": 3,
      "8,21": 3,
      "8,22": 3,
      "8,23": 5,
      "8,27": 6,
      "8,32": 6,
      "8,37": 7,
      "20,1": 0,
      "20,11": 7,
      "20,21": 8,
      "20,25": 9,
      "20,34": 10
    },
    "SheetStyle": {
      "FontFamily": 2
    }
  },
  "Spans": [
    "1,1,2,7",
    "20,34,2,7",
    "9,1,10,40",
    "4,1,2,7",
    "4,17,2,4",
    "4,34,2,7",
    "4,21,2,7",
    "4,8,2,7",
    "1,17,2,4",
    "1,30,2,4",
    "1,8,2,7",
    "20,1,2,10",
    "20,11,2,9",
    "8,14,1,4",
    "8,18,1,5",
    "8,23,1,4",
    "8,37,1,4",
    "4,30,2,4",
    "20,25,2,7",
    "20,21,2,4",
    "1,21,2,7",
    "1,34,2,7",
    "8,6,1,6",
    "8,12,1,2",
    "8,27,1,5",
    "8,32,1,5",
    "7,6,1,6",
    "7,12,1,2",
    "7,14,1,4",
    "7,18,1,5",
    "7,23,1,4",
    "7,27,1,5",
    "7,32,1,5",
    "7,37,1,4"
  ],
  "PageInfo": {
    "$type": "Forguncy.Model.Pages.NormalPage, ServerDesignerCommon",
    "PermissionData": {
      "$type": "Forguncy.RbacPermission.Core.Impl.Page.PagePermissionData, Forguncy.RbacPermission.Core",
      "permissionResource": {
        "$type": "Forguncy.RbacPermission.Core.Impl.Page.PagePermissionResource, Forguncy.RbacPermission.Core"
      },
      "permissionBindings": [
        {
          "$type": "Forguncy.RbacPermission.Core.Impl.Page.PagePermissionBinding, Forguncy.RbacPermission.Core",
          "roleNames": [
            "Administrator",
            "配料操作",
            "配料单复核"
          ]
        }
      ]
    },
    "RowBreakLines": [],
    "RepeatRangeSettings": []
  },
  "PrintInfo": {
    "PaperSize": {},
    "Margin": {}
  }
}//Vuy6YndlGPVNeU3rKjMLcNPS6oIvHewhWnfsoeYVyMyfaOE06LbG0aApLeOSl/aanUq4gPq24PvwwpJq6YLgevmt2801/77SMF39jNR98zEptOuQlsmmR9SH9iWyhIG2bU+zWeUJv5MQFZWuQx4VIe7t/yR7ggqzQvw2q59kH1oF30ABQkt1CG/RcEp7stmUY/POpOyePO6L+C8zLKBiqRN0z0qDIXfVCJGwbh7cEiDknQTXTQWE078WEqUPcqnA/7/xvzh5djKoqovCITQtvuRoodZ1okZ+xIKLkwwZt1pWj8RKbSBhLi5VwSQpn+vP96qtz/bM8OhR2P5x8TC6GdIMyZmqfWXb0i7v72181vQ7rHX6kUKiUiN7REbU5p68aDsVIhiNSxoY2tx3ACZx5nPVgObSjLAoXkvPOrtuttRnTtC4Ocml82ZM1/CrMxElu1bVe2OortqIaa7iPdnLlB4+wy+h6+4+6i33QV6zh2Kw8VveZtBOU7TVo/G82Uk0yI3Ohmb4j/NLUJlL1rGq266I5Ned1KIHRvcZBbgu3e0adfOcya9wLh3c6XkiaytGv4wPH268NILdEZJAf0IHLJ2kxf0/MqjFbMtSJsrFiYKmRZ8jUYBy9RTrqytHdSZZZqEBQJ4+l3L9phAeqCnfvOGRbF7xCJc99oE4VWA5NWxyppClpNFlJJPozVzZrVIWNcqDfZ5z/3q0P+liEM1e+w6IgpkbghoNkjHrs5hNQh4wr2XtoHh4U9P5KHTRF18YXhy9oUYPqAX4GzUErkcxGYVIM/qehronYAzrLr5Cjj7kMcITQ/v7ebtsziRPQ4IsfbzQQ8+1Q73znrCCT0VHKouHY7y6kTYoVYj3/E61UZh4zDSIfe+9oDTCWNM3XwfERPyiSfACO/gRQ1EZr20L1w==|920